asyncdrive/__init__.py
asyncdrive/asyncdrive.py
asyncdrive/utils/__init__.py
asyncdrive/utils/jwt.py
asyncdrive-1.2.4.dist-info/LICENSE
asyncdrive-1.2.4.dist-info/METADATA
asyncdrive-1.2.4.dist-info/WHEEL
asyncdrive-1.2.4.dist-info/top_level.txt
asyncdrive-1.2.4.dist-info/RECORD
