Metadata-Version: 2.1
Name: asyncdrive
Version: 1.2.4
Summary: UNKNOWN
Home-page: https://github.com/Fliqqr/asyncdrive
Author: Fliqqr
Author-email: author@example.com
License: UNKNOWN
Platform: UNKNOWN
Classifier: Programming Language :: Python :: 3
Classifier: License :: OSI Approved :: MIT License
Classifier: Operating System :: OS Independent
Requires-Python: >=3.6
Requires-Dist: aiohttp
Requires-Dist: pyOpenSSL
